odoo8_addon_contract_discount-8.0.1.0.0.99.dev20-py2.7-nspkg.pth
odoo8_addon_contract_discount-8.0.1.0.0.99.dev20.dist-info/METADATA
odoo8_addon_contract_discount-8.0.1.0.0.99.dev20.dist-info/RECORD
odoo8_addon_contract_discount-8.0.1.0.0.99.dev20.dist-info/WHEEL
odoo8_addon_contract_discount-8.0.1.0.0.99.dev20.dist-info/namespace_packages.txt
odoo8_addon_contract_discount-8.0.1.0.0.99.dev20.dist-info/top_level.txt
odoo_addons/contract_discount/README.rst
odoo_addons/contract_discount/__init__.py
odoo_addons/contract_discount/__openerp__.py
odoo_addons/contract_discount/i18n/ca.po
odoo_addons/contract_discount/i18n/contract_discount.pot
odoo_addons/contract_discount/i18n/de.po
odoo_addons/contract_discount/i18n/el_GR.po
odoo_addons/contract_discount/i18n/es.po
odoo_addons/contract_discount/i18n/es_MX.po
odoo_addons/contract_discount/i18n/fi.po
odoo_addons/contract_discount/i18n/fr.po
odoo_addons/contract_discount/i18n/pt_BR.po
odoo_addons/contract_discount/i18n/pt_PT.po
odoo_addons/contract_discount/i18n/ru.po
odoo_addons/contract_discount/i18n/sk_SK.po
odoo_addons/contract_discount/i18n/sl.po
odoo_addons/contract_discount/i18n/tr_TR.po
odoo_addons/contract_discount/i18n/zh_CN.po
odoo_addons/contract_discount/models/__init__.py
odoo_addons/contract_discount/models/contract.py
odoo_addons/contract_discount/static/description/icon.png
odoo_addons/contract_discount/test/contract_discount.yml
odoo_addons/contract_discount/tests/__init__.py
odoo_addons/contract_discount/tests/test_contract_discount.py
odoo_addons/contract_discount/views/contract_view.xml
